[
    {
        "user_id": "U_001",
        "age": 34,
        "occupation": "salaried",
        "monthly_income": 4500.0,
        "transaction_count_30d": 35,
        "avg_transaction_amount": 120.5,
        "location_risk_score": 0.12,
        "device_change_frequency": 1,
        "previous_fraud_flag": 0,
        "account_age_months": 48,
        "chargeback_count": 0
    },
    {
        "user_id": "U_002",
        "age": 26,
        "occupation": "freelancer",
        "monthly_income": 2800.0,
        "transaction_count_30d": 18,
        "avg_transaction_amount": 90.2,
        "location_risk_score": 0.18,
        "device_change_frequency": 2,
        "previous_fraud_flag": 0,
        "account_age_months": 14,
        "chargeback_count": 0
    },
    {
        "user_id": "U_003",
        "age": 41,
        "occupation": "business",
        "monthly_income": 8200.0,
        "transaction_count_30d": 52,
        "avg_transaction_amount": 310.0,
        "location_risk_score": 0.08,
        "device_change_frequency": 1,
        "previous_fraud_flag": 0,
        "account_age_months": 72,
        "chargeback_count": 0
    },
    {
        "user_id": "U_004",
        "age": 22,
        "occupation": "student",
        "monthly_income": 900.0,
        "transaction_count_30d": 9,
        "avg_transaction_amount": 45.0,
        "location_risk_score": 0.25,
        "device_change_frequency": 3,
        "previous_fraud_flag": 0,
        "account_age_months": 6,
        "chargeback_count": 0
    },
    {
        "user_id": "U_005",
        "age": 37,
        "occupation": "salaried",
        "monthly_income": 5200.0,
        "transaction_count_30d": 44,
        "avg_transaction_amount": 140.0,
        "location_risk_score": 0.11,
        "device_change_frequency": 1,
        "previous_fraud_flag": 0,
        "account_age_months": 60,
        "chargeback_count": 0
    },
    {
        "user_id": "U_006",
        "age": 29,
        "occupation": "freelancer",
        "monthly_income": 3100.0,
        "transaction_count_30d": 61,
        "avg_transaction_amount": 75.0,
        "location_risk_score": 0.32,
        "device_change_frequency": 4,
        "previous_fraud_flag": 1,
        "account_age_months": 10,
        "chargeback_count": 2
    },
    {
        "user_id": "U_007",
        "age": 45,
        "occupation": "business",
        "monthly_income": 12000.0,
        "transaction_count_30d": 80,
        "avg_transaction_amount": 520.0,
        "location_risk_score": 0.09,
        "device_change_frequency": 1,
        "previous_fraud_flag": 0,
        "account_age_months": 96,
        "chargeback_count": 0
    },
    {
        "user_id": "U_008",
        "age": 31,
        "occupation": "salaried",
        "monthly_income": 4000.0,
        "transaction_count_30d": 70,
        "avg_transaction_amount": 60.0,
        "location_risk_score": 0.41,
        "device_change_frequency": 5,
        "previous_fraud_flag": 1,
        "account_age_months": 8,
        "chargeback_count": 3
    },
    {
        "user_id": "U_009",
        "age": 38,
        "occupation": "business",
        "monthly_income": 6700.0,
        "transaction_count_30d": 25,
        "avg_transaction_amount": 210.0,
        "location_risk_score": 0.15,
        "device_change_frequency": 2,
        "previous_fraud_flag": 0,
        "account_age_months": 40,
        "chargeback_count": 1
    },
    {
        "user_id": "U_010",
        "age": 24,
        "occupation": "student",
        "monthly_income": 1100.0,
        "transaction_count_30d": 48,
        "avg_transaction_amount": 35.0,
        "location_risk_score": 0.48,
        "device_change_frequency": 6,
        "previous_fraud_flag": 1,
        "account_age_months": 4,
        "chargeback_count": 4
    },
    {
        "user_id": "U_011",
        "age": 50,
        "occupation": "salaried",
        "monthly_income": 9000.0,
        "transaction_count_30d": 30,
        "avg_transaction_amount": 300.0,
        "location_risk_score": 0.10,
        "device_change_frequency": 1,
        "previous_fraud_flag": 0,
        "account_age_months": 120,
        "chargeback_count": 0
    },
    {
        "user_id": "U_012",
        "age": 27,
        "occupation": "freelancer",
        "monthly_income": 2600.0,
        "transaction_count_30d": 55,
        "avg_transaction_amount": 85.0,
        "location_risk_score": 0.36,
        "device_change_frequency": 4,
        "previous_fraud_flag": 1,
        "account_age_months": 9,
        "chargeback_count": 2
    },
    {
        "user_id": "U_013",
        "age": 35,
        "occupation": "salaried",
        "monthly_income": 4800.0,
        "transaction_count_30d": 40,
        "avg_transaction_amount": 130.0,
        "location_risk_score": 0.14,
        "device_change_frequency": 2,
        "previous_fraud_flag": 0,
        "account_age_months": 36,
        "chargeback_count": 0
    },
    {
        "user_id": "U_014",
        "age": 23,
        "occupation": "student",
        "monthly_income": 800.0,
        "transaction_count_30d": 65,
        "avg_transaction_amount": 28.0,
        "location_risk_score": 0.52,
        "device_change_frequency": 7,
        "previous_fraud_flag": 1,
        "account_age_months": 3,
        "chargeback_count": 5
    },
    {
        "user_id": "U_015",
        "age": 42,
        "occupation": "business",
        "monthly_income": 7500.0,
        "transaction_count_30d": 20,
        "avg_transaction_amount": 260.0,
        "location_risk_score": 0.13,
        "device_change_frequency": 1,
        "previous_fraud_flag": 0,
        "account_age_months": 68,
        "chargeback_count": 0
    },
    {
        "user_id": "U_031",
        "age": 33,
        "occupation": "salaried",
        "monthly_income": 5100.0,
        "transaction_count_30d": 38,
        "avg_transaction_amount": 145.0,
        "location_risk_score": 0.11,
        "device_change_frequency": 1,
        "previous_fraud_flag": 0,
        "account_age_months": 54,
        "chargeback_count": 0
    },
    {
        "user_id": "U_032",
        "age": 28,
        "occupation": "freelancer",
        "monthly_income": 2900.0,
        "transaction_count_30d": 47,
        "avg_transaction_amount": 92.0,
        "location_risk_score": 0.21,
        "device_change_frequency": 2,
        "previous_fraud_flag": 0,
        "account_age_months": 18,
        "chargeback_count": 1
    },
    {
        "user_id": "U_033",
        "age": 46,
        "occupation": "business",
        "monthly_income": 9800.0,
        "transaction_count_30d": 60,
        "avg_transaction_amount": 420.0,
        "location_risk_score": 0.09,
        "device_change_frequency": 1,
        "previous_fraud_flag": 0,
        "account_age_months": 84,
        "chargeback_count": 0
    },
    {
        "user_id": "U_034",
        "age": 21,
        "occupation": "student",
        "monthly_income": 750.0,
        "transaction_count_30d": 72,
        "avg_transaction_amount": 30.0,
        "location_risk_score": 0.55,
        "device_change_frequency": 8,
        "previous_fraud_flag": 1,
        "account_age_months": 2,
        "chargeback_count": 6
    },
    {
        "user_id": "U_035",
        "age": 39,
        "occupation": "salaried",
        "monthly_income": 6000.0,
        "transaction_count_30d": 42,
        "avg_transaction_amount": 160.0,
        "location_risk_score": 0.13,
        "device_change_frequency": 1,
        "previous_fraud_flag": 0,
        "account_age_months": 66,
        "chargeback_count": 0
    },
    {
        "user_id": "U_036",
        "age": 31,
        "occupation": "freelancer",
        "monthly_income": 3300.0,
        "transaction_count_30d": 58,
        "avg_transaction_amount": 88.0,
        "location_risk_score": 0.34,
        "device_change_frequency": 3,
        "previous_fraud_flag": 1,
        "account_age_months": 11,
        "chargeback_count": 2
    },
    {
        "user_id": "U_037",
        "age": 52,
        "occupation": "business",
        "monthly_income": 11000.0,
        "transaction_count_30d": 28,
        "avg_transaction_amount": 480.0,
        "location_risk_score": 0.10,
        "device_change_frequency": 1,
        "previous_fraud_flag": 0,
        "account_age_months": 132,
        "chargeback_count": 0
    },
    {
        "user_id": "U_038",
        "age": 27,
        "occupation": "student",
        "monthly_income": 950.0,
        "transaction_count_30d": 50,
        "avg_transaction_amount": 40.0,
        "location_risk_score": 0.47,
        "device_change_frequency": 6,
        "previous_fraud_flag": 1,
        "account_age_months": 5,
        "chargeback_count": 3
    },
    {
        "user_id": "U_039",
        "age": 44,
        "occupation": "salaried",
        "monthly_income": 7800.0,
        "transaction_count_30d": 33,
        "avg_transaction_amount": 230.0,
        "location_risk_score": 0.12,
        "device_change_frequency": 1,
        "previous_fraud_flag": 0,
        "account_age_months": 90,
        "chargeback_count": 0
    },
    {
        "user_id": "U_040",
        "age": 30,
        "occupation": "freelancer",
        "monthly_income": 2600.0,
        "transaction_count_30d": 64,
        "avg_transaction_amount": 70.0,
        "location_risk_score": 0.38,
        "device_change_frequency": 4,
        "previous_fraud_flag": 1,
        "account_age_months": 7,
        "chargeback_count": 2
    },
    {
        "user_id": "U_041",
        "age": 36,
        "occupation": "business",
        "monthly_income": 8800.0,
        "transaction_count_30d": 22,
        "avg_transaction_amount": 340.0,
        "location_risk_score": 0.14,
        "device_change_frequency": 2,
        "previous_fraud_flag": 0,
        "account_age_months": 58,
        "chargeback_count": 1
    },
    {
        "user_id": "U_042",
        "age": 24,
        "occupation": "student",
        "monthly_income": 820.0,
        "transaction_count_30d": 68,
        "avg_transaction_amount": 33.0,
        "location_risk_score": 0.51,
        "device_change_frequency": 7,
        "previous_fraud_flag": 1,
        "account_age_months": 4,
        "chargeback_count": 4
    },
    {
        "user_id": "U_043",
        "age": 48,
        "occupation": "salaried",
        "monthly_income": 9200.0,
        "transaction_count_30d": 26,
        "avg_transaction_amount": 310.0,
        "location_risk_score": 0.09,
        "device_change_frequency": 1,
        "previous_fraud_flag": 0,
        "account_age_months": 110,
        "chargeback_count": 0
    },
    {
        "user_id": "U_044",
        "age": 29,
        "occupation": "freelancer",
        "monthly_income": 3000.0,
        "transaction_count_30d": 53,
        "avg_transaction_amount": 95.0,
        "location_risk_score": 0.29,
        "device_change_frequency": 3,
        "previous_fraud_flag": 0,
        "account_age_months": 20,
        "chargeback_count": 1
    },
    {
        "user_id": "U_045",
        "age": 41,
        "occupation": "business",
        "monthly_income": 10500.0,
        "transaction_count_30d": 48,
        "avg_transaction_amount": 390.0,
        "location_risk_score": 0.12,
        "device_change_frequency": 1,
        "previous_fraud_flag": 0,
        "account_age_months": 75,
        "chargeback_count": 0
    }
]